dan_airflow/__init__.py
dan_airflow/_project.py
dan_airflow/_version.py
dan_airflow/operators/__init__.py
dan_airflow/operators/dan_operator.py
dan_airflow-0.1.0.dist-info/METADATA
dan_airflow-0.1.0.dist-info/WHEEL
dan_airflow-0.1.0.dist-info/top_level.txt
dan_airflow-0.1.0.dist-info/RECORD
