Metadata-Version: 2.1
Name: dan-airflow
Version: 0.1.0
Summary: Airflow plugins for Dan Conger
Home-page: UNKNOWN
Author: Dan Conger
Author-email: UNKNOWN
License: Apache License Version 2.0
Keywords: airflow
Platform: UNKNOWN
Requires-Dist: apache-airflow (>=1.10.9)
